qquant/__init__.py
qquant/version.py
qquant-0.0.0.dist-info/METADATA
qquant-0.0.0.dist-info/WHEEL
qquant-0.0.0.dist-info/top_level.txt
qquant-0.0.0.dist-info/RECORD
