Metadata-Version: 2.1
Name: qquant
Version: 0.0.0
Summary: qquant
Home-page: http://pypi.org/project/qquant
License: UNKNOWN
Platform: UNKNOWN
Classifier: Programming Language :: Python
Classifier: Intended Audience :: Science/Research
